{"object-stream":{"list":[{"models.Note":[{"noteTitle":"dd","notePriority":5,"noteCategory":"dd","isNoteArchived":true},{"noteTitle":"ff","notePriority":5,"noteCategory":"ff","isNoteArchived":false},{"noteTitle":"rr","notePriority":5,"noteCategory":"rr","isNoteArchived":false},{"noteTitle":"gg","notePriority":5,"noteCategory":"gg","isNoteArchived":false},{"noteTitle":"ww","notePriority":5,"noteCategory":"ww","isNoteArchived":false},{"noteTitle":"ww","notePriority":4,"noteCategory":"ww","isNoteArchived":false},{"noteTitle":"ee","notePriority":3,"noteCategory":"ee","isNoteArchived":false},{"noteTitle":"tt","notePriority":5,"noteCategory":"tt","isNoteArchived":false},{"noteTitle":"bb","notePriority":2,"noteCategory":"bb","isNoteArchived":false}]}]}}